CoreDataX/CDX.py
CoreDataX/example.csv
CoreDataX/loader.py
CoreDataX/requirements.txt
CoreDataX/server.py
coredatax-0.9.0.dist-info/METADATA
coredatax-0.9.0.dist-info/WHEEL
coredatax-0.9.0.dist-info/RECORD
